setup.py
gaussian_udacity_distribution/Binomialdistribution.py
gaussian_udacity_distribution/Gaussiandistribution.py
gaussian_udacity_distribution/Generaldistribution.py
gaussian_udacity_distribution/__init__.py
gaussian_udacity_distribution.egg-info/PKG-INFO
gaussian_udacity_distribution.egg-info/SOURCES.txt
gaussian_udacity_distribution.egg-info/dependency_links.txt
gaussian_udacity_distribution.egg-info/not-zip-safe
gaussian_udacity_distribution.egg-info/top_level.txt